README.md
setup.py
CubeStories/__init__.py
CubeStories/cubeParameters/__init__.py
CubeStories/cubeParameters/cubeParameters.py
CubeStories/metaData/__init__.py
CubeStories/metaData/metaData.py
CubeStories/storyPattern/__init__.py
CubeStories/storyPattern/analysisByCategory.py
CubeStories/storyPattern/dissFactors.py
CubeStories/storyPattern/exploreIntersection.py
CubeStories/storyPattern/extComparison.py
CubeStories/storyPattern/highContrast.py
CubeStories/storyPattern/intComparison.py
CubeStories/storyPattern/leagueTable.py
CubeStories/storyPattern/measCount.py
CubeStories/storyPattern/narrChangeOT.py
CubeStories/storyPattern/profOutliers.py
CubeStories/storyPattern/startBigDrillDown.py
CubeStories/storyPattern/startSmallZoomOut.py
CubeStories/storyPattern/storyPattern.py
CubeStories/storyTeller/__init__.py
CubeStories/storyTeller/storyTeller.py
cubestories.egg-info/PKG-INFO
cubestories.egg-info/SOURCES.txt
cubestories.egg-info/dependency_links.txt
cubestories.egg-info/not-zip-safe
cubestories.egg-info/requires.txt
cubestories.egg-info/top_level.txt