Metadata-Version: 2.1
Name: cubestories
Version: 0.3.11
Summary: CuebStories
Home-page: https://github.com/MaciejJanowski/CubeStories
Author: Maciej Janowski
Author-email: maciej.janowski@insight-centre.org
License: MIT
Platform: UNKNOWN
